{
	"version": 4,
	"player_pos": [
		562.00000000,
		453.00000000
	],
	"portal_pos": [
		656.00000000,
		232.00000000
	],
	"enemies": [

	],
	"enemy_data": [
		{
			"id": [
				221,
				117,
				179,
				164,
				99,
				63,
				76,
				11,
				188,
				37,
				203,
				126,
				95,
				171,
				153,
				88
			],
			"pos": [
				617.00000000,
				475.00000000
			],
			"start_disabled": false,
			"look_angle": -107.67790985,
			"health": 80.00000000,
			"max_health": 80.00000000,
			"variant": 0
		},
		{
			"id": [
				191,
				166,
				40,
				93,
				229,
				92,
				70,
				41,
				168,
				56,
				56,
				222,
				148,
				125,
				51,
				213
			],
			"pos": [
				710.00000000,
				483.00000000
			],
			"start_disabled": false,
			"look_angle": 180.00000000,
			"health": 80.00000000,
			"max_health": 80.00000000,
			"variant": 1
		},
		{
			"id": [
				195,
				111,
				205,
				105,
				46,
				37,
				79,
				47,
				184,
				200,
				191,
				184,
				23,
				28,
				31,
				99
			],
			"pos": [
				596.00000000,
				231.00000000
			],
			"start_disabled": false,
			"look_angle": 78.61465454,
			"health": 80.00000000,
			"max_health": 80.00000000,
			"variant": 1
		},
		{
			"id": [
				152,
				238,
				114,
				53,
				81,
				160,
				72,
				138,
				189,
				120,
				20,
				9,
				10,
				201,
				87,
				216
			],
			"pos": [
				587.00000000,
				329.00000000
			],
			"start_disabled": false,
			"look_angle": 65.39987946,
			"health": 80.00000000,
			"max_health": 80.00000000,
			"variant": 0
		},
		{
			"id": [
				83,
				216,
				210,
				199,
				87,
				170,
				74,
				37,
				156,
				13,
				25,
				89,
				26,
				39,
				166,
				59
			],
			"pos": [
				744.00000000,
				387.00000000
			],
			"start_disabled": false,
			"look_angle": 86.76226807,
			"health": 80.00000000,
			"max_health": 80.00000000,
			"variant": 0
		},
		{
			"id": [
				140,
				54,
				153,
				65,
				247,
				172,
				74,
				144,
				151,
				129,
				32,
				232,
				167,
				135,
				154,
				187
			],
			"pos": [
				704.00000000,
				232.00000000
			],
			"start_disabled": false,
			"look_angle": 73.17374420,
			"health": 80.00000000,
			"max_health": 80.00000000,
			"variant": 1
		},
		{
			"id": [
				232,
				116,
				191,
				101,
				9,
				230,
				74,
				217,
				145,
				175,
				193,
				239,
				145,
				48,
				56,
				42
			],
			"pos": [
				646.00000000,
				317.00000000
			],
			"start_disabled": false,
			"look_angle": 66.77731323,
			"health": 80.00000000,
			"max_health": 80.00000000,
			"variant": 0
		},
		{
			"id": [
				94,
				71,
				83,
				107,
				59,
				104,
				78,
				201,
				176,
				230,
				4,
				85,
				115,
				197,
				53,
				230
			],
			"pos": [
				736.00000000,
				309.00000000
			],
			"start_disabled": false,
			"look_angle": 85.05158234,
			"health": 80.00000000,
			"max_health": 80.00000000,
			"variant": 0
		},
		{
			"id": [
				18,
				217,
				1,
				12,
				219,
				139,
				66,
				239,
				146,
				146,
				163,
				221,
				21,
				11,
				143,
				173
			],
			"pos": [
				615.00000000,
				256.00000000
			],
			"start_disabled": false,
			"look_angle": 113.52305603,
			"health": 80.00000000,
			"max_health": 80.00000000,
			"variant": 0
		},
		{
			"id": [
				223,
				145,
				208,
				54,
				65,
				118,
				72,
				121,
				160,
				112,
				227,
				250,
				220,
				5,
				123,
				153
			],
			"pos": [
				706.00000000,
				427.00000000
			],
			"start_disabled": false,
			"look_angle": 13.48024273,
			"health": 80.00000000,
			"max_health": 80.00000000,
			"variant": 0
		}
	],
	"items": [
		{
			"moving_entity": {
				"physics_entity": {
					"entity": {
						"id": [
							250,
							16,
							170,
							74,
							253,
							101,
							77,
							193,
							186,
							152,
							248,
							38,
							161,
							35,
							182,
							172
						],
						"pos": [
							590.00000000,
							446.00000000
						],
						"queue_free": false,
						"start_disabled": false
					},
					"shape": {
						"pos": [
							0.00000000,
							0.00000000
						],
						"radius": 4.00000000
					}
				},
				"vel": [
					0.00000000,
					0.00000000
				]
			},
			"data": {
				"id": 1,
				"count": 1,
				"max_count": 0
			}
		},
		{
			"moving_entity": {
				"physics_entity": {
					"entity": {
						"id": [
							248,
							201,
							99,
							199,
							244,
							124,
							65,
							189,
							139,
							223,
							7,
							30,
							240,
							96,
							151,
							150
						],
						"pos": [
							716.00000000,
							390.00000000
						],
						"queue_free": false,
						"start_disabled": false
					},
					"shape": {
						"pos": [
							0.00000000,
							0.00000000
						],
						"radius": 4.00000000
					}
				},
				"vel": [
					0.00000000,
					0.00000000
				]
			},
			"data": {
				"id": 1,
				"count": 1,
				"max_count": 0
			}
		}
	],
	"exploding_barrels": [
		{
			"moving_entity": {
				"physics_entity": {
					"entity": {
						"id": [
							227,
							64,
							237,
							127,
							86,
							20,
							66,
							194,
							176,
							124,
							150,
							82,
							6,
							71,
							61,
							81
						],
						"pos": [
							716.00000000,
							288.00000000
						],
						"queue_free": false,
						"start_disabled": false
					},
					"shape": {
						"pos": [
							0.00000000,
							0.00000000
						],
						"radius": 6.00000000
					}
				},
				"vel": [
					0.00000000,
					0.00000000
				]
			},
			"health": 50.00000000,
			"max_health": 50.00000000,
			"exploding": false,
			"explosion_timer": 0.00000000
		},
		{
			"moving_entity": {
				"physics_entity": {
					"entity": {
						"id": [
							109,
							189,
							13,
							231,
							163,
							193,
							65,
							59,
							175,
							246,
							134,
							36,
							114,
							118,
							146,
							12
						],
						"pos": [
							707.00000000,
							403.00000000
						],
						"queue_free": false,
						"start_disabled": false
					},
					"shape": {
						"pos": [
							0.00000000,
							0.00000000
						],
						"radius": 6.00000000
					}
				},
				"vel": [
					0.00000000,
					0.00000000
				]
			},
			"health": 50.00000000,
			"max_health": 50.00000000,
			"exploding": false,
			"explosion_timer": 0.00000000
		},
		{
			"moving_entity": {
				"physics_entity": {
					"entity": {
						"id": [
							102,
							70,
							183,
							212,
							196,
							52,
							68,
							194,
							167,
							100,
							107,
							138,
							202,
							51,
							77,
							249
						],
						"pos": [
							604.00000000,
							384.00000000
						],
						"queue_free": false,
						"start_disabled": false
					},
					"shape": {
						"pos": [
							0.00000000,
							0.00000000
						],
						"radius": 6.00000000
					}
				},
				"vel": [
					0.00000000,
					0.00000000
				]
			},
			"health": 50.00000000,
			"max_health": 50.00000000,
			"exploding": false,
			"explosion_timer": 0.00000000
		}
	],
	"walls": [
		{
			"entity": {
				"id": [
					190,
					155,
					236,
					197,
					199,
					158,
					73,
					74,
					172,
					40,
					68,
					9,
					248,
					168,
					244,
					96
				],
				"pos": [
					520.00000000,
					368.00000000
				],
				"queue_free": false,
				"start_disabled": false
			},
			"shape": {
				"x": 0.00000000,
				"y": 0.00000000,
				"width": 8.00000000,
				"height": 128.00000000
			}
		},
		{
			"entity": {
				"id": [
					10,
					178,
					136,
					33,
					199,
					47,
					77,
					184,
					158,
					235,
					237,
					102,
					84,
					222,
					201,
					187
				],
				"pos": [
					568.00000000,
					408.00000000
				],
				"queue_free": false,
				"start_disabled": false
			},
			"shape": {
				"x": 0.00000000,
				"y": 0.00000000,
				"width": 88.00000000,
				"height": 8.00000000
			}
		},
		{
			"entity": {
				"id": [
					145,
					253,
					143,
					255,
					84,
					98,
					75,
					113,
					183,
					14,
					104,
					216,
					212,
					106,
					199,
					109
				],
				"pos": [
					568.00000000,
					440.00000000
				],
				"queue_free": false,
				"start_disabled": false
			},
			"shape": {
				"x": 0.00000000,
				"y": 0.00000000,
				"width": 8.00000000,
				"height": 32.00000000
			}
		},
		{
			"entity": {
				"id": [
					152,
					235,
					170,
					41,
					194,
					150,
					70,
					177,
					137,
					67,
					203,
					146,
					214,
					169,
					125,
					212
				],
				"pos": [
					520.00000000,
					496.00000000
				],
				"queue_free": false,
				"start_disabled": false
			},
			"shape": {
				"x": 0.00000000,
				"y": 0.00000000,
				"width": 248.00000000,
				"height": 8.00000000
			}
		},
		{
			"entity": {
				"id": [
					0,
					186,
					179,
					93,
					18,
					184,
					70,
					143,
					184,
					12,
					229,
					19,
					81,
					15,
					160,
					48
				],
				"pos": [
					688.00000000,
					408.00000000
				],
				"queue_free": false,
				"start_disabled": false
			},
			"shape": {
				"x": 0.00000000,
				"y": 0.00000000,
				"width": 8.00000000,
				"height": 40.00000000
			}
		},
		{
			"entity": {
				"id": [
					201,
					245,
					101,
					112,
					34,
					147,
					65,
					118,
					154,
					170,
					44,
					19,
					162,
					89,
					201,
					176
				],
				"pos": [
					768.00000000,
					256.00000000
				],
				"queue_free": false,
				"start_disabled": false
			},
			"shape": {
				"x": 0.00000000,
				"y": 0.00000000,
				"width": 8.00000000,
				"height": 248.00000000
			}
		},
		{
			"entity": {
				"id": [
					96,
					243,
					117,
					87,
					12,
					134,
					76,
					109,
					159,
					227,
					174,
					67,
					253,
					178,
					209,
					255
				],
				"pos": [
					688.00000000,
					320.00000000
				],
				"queue_free": false,
				"start_disabled": false
			},
			"shape": {
				"x": 0.00000000,
				"y": 0.00000000,
				"width": 8.00000000,
				"height": 40.00000000
			}
		},
		{
			"entity": {
				"id": [
					3,
					144,
					233,
					226,
					144,
					106,
					66,
					62,
					191,
					118,
					157,
					248,
					12,
					86,
					189,
					145
				],
				"pos": [
					672.00000000,
					312.00000000
				],
				"queue_free": false,
				"start_disabled": false
			},
			"shape": {
				"x": 0.00000000,
				"y": 0.00000000,
				"width": 24.00000000,
				"height": 8.00000000
			}
		},
		{
			"entity": {
				"id": [
					224,
					139,
					196,
					27,
					36,
					38,
					65,
					143,
					170,
					242,
					200,
					14,
					235,
					146,
					189,
					225
				],
				"pos": [
					624.00000000,
					304.00000000
				],
				"queue_free": false,
				"start_disabled": false
			},
			"shape": {
				"x": 0.00000000,
				"y": 0.00000000,
				"width": 8.00000000,
				"height": 56.00000000
			}
		},
		{
			"entity": {
				"id": [
					213,
					208,
					248,
					168,
					10,
					78,
					69,
					33,
					174,
					14,
					132,
					195,
					200,
					254,
					160,
					8
				],
				"pos": [
					624.00000000,
					256.00000000
				],
				"queue_free": false,
				"start_disabled": false
			},
			"shape": {
				"x": 0.00000000,
				"y": 0.00000000,
				"width": 16.00000000,
				"height": 8.00000000
			}
		},
		{
			"entity": {
				"id": [
					39,
					127,
					83,
					248,
					190,
					27,
					69,
					9,
					174,
					183,
					74,
					148,
					63,
					125,
					196,
					8
				],
				"pos": [
					672.00000000,
					256.00000000
				],
				"queue_free": false,
				"start_disabled": false
			},
			"shape": {
				"x": 0.00000000,
				"y": 0.00000000,
				"width": 16.00000000,
				"height": 8.00000000
			}
		},
		{
			"entity": {
				"id": [
					9,
					63,
					159,
					192,
					248,
					37,
					72,
					4,
					151,
					85,
					84,
					145,
					141,
					34,
					220,
					65
				],
				"pos": [
					576.00000000,
					200.00000000
				],
				"queue_free": false,
				"start_disabled": false
			},
			"shape": {
				"x": 0.00000000,
				"y": 0.00000000,
				"width": 168.00000000,
				"height": 8.00000000
			}
		},
		{
			"entity": {
				"id": [
					244,
					152,
					50,
					187,
					133,
					209,
					79,
					154,
					178,
					135,
					119,
					186,
					153,
					60,
					127,
					22
				],
				"pos": [
					728.00000000,
					376.00000000
				],
				"queue_free": false,
				"start_disabled": false
			},
			"shape": {
				"x": 0.00000000,
				"y": 0.00000000,
				"width": 8.00000000,
				"height": 32.00000000
			}
		},
		{
			"entity": {
				"id": [
					233,
					114,
					103,
					69,
					7,
					23,
					67,
					144,
					139,
					75,
					65,
					79,
					171,
					236,
					78,
					109
				],
				"pos": [
					680.00000000,
					208.00000000
				],
				"queue_free": false,
				"start_disabled": false
			},
			"shape": {
				"x": 0.00000000,
				"y": 0.00000000,
				"width": 8.00000000,
				"height": 56.00000000
			}
		},
		{
			"entity": {
				"id": [
					48,
					4,
					41,
					61,
					86,
					80,
					70,
					168,
					187,
					23,
					192,
					74,
					152,
					194,
					132,
					150
				],
				"pos": [
					720.00000000,
					320.00000000
				],
				"queue_free": false,
				"start_disabled": false
			},
			"shape": {
				"x": 0.00000000,
				"y": 0.00000000,
				"width": 32.00000000,
				"height": 8.00000000
			}
		},
		{
			"entity": {
				"id": [
					48,
					87,
					80,
					183,
					59,
					185,
					68,
					28,
					157,
					97,
					220,
					108,
					243,
					22,
					156,
					201
				],
				"pos": [
					568.00000000,
					200.00000000
				],
				"queue_free": false,
				"start_disabled": false
			},
			"shape": {
				"x": 0.00000000,
				"y": 0.00000000,
				"width": 8.00000000,
				"height": 168.00000000
			}
		},
		{
			"entity": {
				"id": [
					196,
					53,
					24,
					47,
					40,
					255,
					73,
					251,
					182,
					106,
					49,
					250,
					157,
					215,
					165,
					8
				],
				"pos": [
					736.00000000,
					256.00000000
				],
				"queue_free": false,
				"start_disabled": false
			},
			"shape": {
				"x": 0.00000000,
				"y": 0.00000000,
				"width": 40.00000000,
				"height": 8.00000000
			}
		},
		{
			"entity": {
				"id": [
					234,
					148,
					156,
					216,
					116,
					25,
					76,
					72,
					166,
					48,
					6,
					247,
					239,
					233,
					131,
					225
				],
				"pos": [
					736.00000000,
					208.00000000
				],
				"queue_free": false,
				"start_disabled": false
			},
			"shape": {
				"x": 0.00000000,
				"y": 0.00000000,
				"width": 8.00000000,
				"height": 56.00000000
			}
		},
		{
			"entity": {
				"id": [
					238,
					42,
					187,
					126,
					245,
					80,
					78,
					3,
					148,
					109,
					94,
					197,
					93,
					224,
					180,
					232
				],
				"pos": [
					648.00000000,
					440.00000000
				],
				"queue_free": false,
				"start_disabled": false
			},
			"shape": {
				"x": 0.00000000,
				"y": 0.00000000,
				"width": 8.00000000,
				"height": 32.00000000
			}
		},
		{
			"entity": {
				"id": [
					124,
					205,
					200,
					197,
					186,
					93,
					68,
					42,
					140,
					102,
					169,
					173,
					57,
					232,
					137,
					10
				],
				"pos": [
					520.00000000,
					360.00000000
				],
				"queue_free": false,
				"start_disabled": false
			},
			"shape": {
				"x": 0.00000000,
				"y": 0.00000000,
				"width": 56.00000000,
				"height": 8.00000000
			}
		}
	],
	"half_walls": [
		{
			"physics_entity": {
				"entity": {
					"id": [
						4,
						3,
						83,
						165,
						135,
						167,
						74,
						124,
						153,
						26,
						65,
						56,
						75,
						7,
						176,
						96
					],
					"pos": [
						640.00000000,
						256.00000000
					],
					"queue_free": false,
					"start_disabled": false
				},
				"shape": {
					"x": 0.00000000,
					"y": 0.00000000,
					"width": 32.00000000,
					"height": 8.00000000
				}
			}
		},
		{
			"physics_entity": {
				"entity": {
					"id": [
						96,
						112,
						129,
						125,
						178,
						28,
						78,
						209,
						137,
						25,
						44,
						117,
						239,
						73,
						38,
						152
					],
					"pos": [
						624.00000000,
						264.00000000
					],
					"queue_free": false,
					"start_disabled": false
				},
				"shape": {
					"x": 0.00000000,
					"y": 0.00000000,
					"width": 8.00000000,
					"height": 40.00000000
				}
			}
		},
		{
			"physics_entity": {
				"entity": {
					"id": [
						157,
						105,
						253,
						177,
						107,
						176,
						73,
						77,
						163,
						39,
						8,
						75,
						5,
						169,
						190,
						84
					],
					"pos": [
						656.00000000,
						408.00000000
					],
					"queue_free": false,
					"start_disabled": false
				},
				"shape": {
					"x": 0.00000000,
					"y": 0.00000000,
					"width": 32.00000000,
					"height": 8.00000000
				}
			}
		}
	],
	"bounds": {
		"x": 0.00000000,
		"y": 0.00000000,
		"width": 0.00000000,
		"height": 0.00000000
	},
	"has_tutorial": false,
	"save_after_completion": true
}