{
	"player_pos": [
		837.00000000,
		581.00000000
	],
	"portal_pos": [
		923.00000000,
		488.00000000
	],
	"enemies": [

	],
	"enemy_data": [
		{
			"id": [
				4,
				62,
				190,
				109,
				155,
				164,
				75,
				74,
				158,
				21,
				77,
				81,
				91,
				205,
				187,
				173
			],
			"pos": [
				838.00000000,
				396.00000000
			],
			"start_disabled": false,
			"look_angle": 0.00000000,
			"health": 80.00000000,
			"max_health": 80.00000000,
			"variant": 1
		},
		{
			"id": [
				75,
				225,
				241,
				95,
				69,
				202,
				65,
				59,
				131,
				116,
				170,
				251,
				83,
				210,
				67,
				170
			],
			"pos": [
				829.00000000,
				462.00000000
			],
			"start_disabled": false,
			"look_angle": 0.00000000,
			"health": 80.00000000,
			"max_health": 80.00000000,
			"variant": 0
		},
		{
			"id": [
				75,
				116,
				165,
				9,
				29,
				255,
				77,
				223,
				191,
				68,
				203,
				128,
				211,
				48,
				176,
				111
			],
			"pos": [
				923.00000000,
				488.00000000
			],
			"start_disabled": false,
			"look_angle": 0.00000000,
			"health": 80.00000000,
			"max_health": 80.00000000,
			"variant": 0
		}
	],
	"items": [

	],
	"exploding_barrels": [

	],
	"walls": [
		{
			"entity": {
				"id": [
					224,
					49,
					11,
					199,
					200,
					5,
					77,
					72,
					181,
					67,
					79,
					44,
					188,
					252,
					50,
					33
				],
				"pos": [
					888.00000000,
					448.00000000
				],
				"queue_free": false,
				"start_disabled": false
			},
			"shape": {
				"x": 0.00000000,
				"y": 0.00000000,
				"width": 80.00000000,
				"height": 8.00000000
			}
		},
		{
			"entity": {
				"id": [
					188,
					72,
					248,
					10,
					107,
					99,
					65,
					201,
					163,
					185,
					236,
					241,
					181,
					38,
					244,
					19
				],
				"pos": [
					888.00000000,
					520.00000000
				],
				"queue_free": false,
				"start_disabled": false
			},
			"shape": {
				"x": 0.00000000,
				"y": 0.00000000,
				"width": 80.00000000,
				"height": 8.00000000
			}
		},
		{
			"entity": {
				"id": [
					240,
					203,
					179,
					133,
					96,
					67,
					66,
					20,
					187,
					140,
					234,
					72,
					56,
					143,
					85,
					102
				],
				"pos": [
					960.00000000,
					448.00000000
				],
				"queue_free": false,
				"start_disabled": false
			},
			"shape": {
				"x": 0.00000000,
				"y": 0.00000000,
				"width": 8.00000000,
				"height": 80.00000000
			}
		},
		{
			"entity": {
				"id": [
					164,
					253,
					20,
					188,
					221,
					157,
					64,
					90,
					163,
					233,
					107,
					248,
					4,
					128,
					100,
					66
				],
				"pos": [
					776.00000000,
					360.00000000
				],
				"queue_free": false,
				"start_disabled": false
			},
			"shape": {
				"x": 0.00000000,
				"y": 0.00000000,
				"width": 8.00000000,
				"height": 168.00000000
			}
		},
		{
			"entity": {
				"id": [
					65,
					64,
					241,
					191,
					7,
					247,
					71,
					192,
					151,
					21,
					172,
					102,
					88,
					15,
					114,
					190
				],
				"pos": [
					776.00000000,
					360.00000000
				],
				"queue_free": false,
				"start_disabled": false
			},
			"shape": {
				"x": 0.00000000,
				"y": 0.00000000,
				"width": 120.00000000,
				"height": 8.00000000
			}
		},
		{
			"entity": {
				"id": [
					29,
					196,
					40,
					139,
					195,
					194,
					72,
					96,
					146,
					1,
					164,
					235,
					189,
					248,
					133,
					234
				],
				"pos": [
					888.00000000,
					368.00000000
				],
				"queue_free": false,
				"start_disabled": false
			},
			"shape": {
				"x": 0.00000000,
				"y": 0.00000000,
				"width": 8.00000000,
				"height": 88.00000000
			}
		}
	],
	"half_walls": [

	],
	"bounds": {
		"x": 0.00000000,
		"y": 0.00000000,
		"width": 0.00000000,
		"height": 0.00000000
	},
	"has_tutorial": false
}